odoo8_addon_sale_order_project-8.0.1.0.0.99.dev21-py3.8-nspkg.pth
odoo_addons/sale_order_project/README.rst
odoo_addons/sale_order_project/__init__.py
odoo_addons/sale_order_project/__openerp__.py
odoo_addons/sale_order_project/i18n/ca.po
odoo_addons/sale_order_project/i18n/de.po
odoo_addons/sale_order_project/i18n/es.po
odoo_addons/sale_order_project/i18n/es_ES.po
odoo_addons/sale_order_project/i18n/es_MX.po
odoo_addons/sale_order_project/i18n/fi.po
odoo_addons/sale_order_project/i18n/fr.po
odoo_addons/sale_order_project/i18n/hr.po
odoo_addons/sale_order_project/i18n/hu.po
odoo_addons/sale_order_project/i18n/it.po
odoo_addons/sale_order_project/i18n/nl.po
odoo_addons/sale_order_project/i18n/nl_NL.po
odoo_addons/sale_order_project/i18n/pt.po
odoo_addons/sale_order_project/i18n/pt_BR.po
odoo_addons/sale_order_project/i18n/pt_PT.po
odoo_addons/sale_order_project/i18n/ro.po
odoo_addons/sale_order_project/i18n/sale_order_project.pot
odoo_addons/sale_order_project/i18n/sk.po
odoo_addons/sale_order_project/i18n/sl.po
odoo_addons/sale_order_project/i18n/tr.po
odoo_addons/sale_order_project/i18n/tr_TR.po
odoo_addons/sale_order_project/i18n/zh_CN.po
odoo_addons/sale_order_project/models/__init__.py
odoo_addons/sale_order_project/models/sale.py
odoo_addons/sale_order_project/static/description/icon.png
odoo_addons/sale_order_project/tests/__init__.py
odoo_addons/sale_order_project/tests/test_sale_order_project.py
odoo_addons/sale_order_project/views/sale_view.xml
odoo8_addon_sale_order_project-8.0.1.0.0.99.dev21.dist-info/METADATA
odoo8_addon_sale_order_project-8.0.1.0.0.99.dev21.dist-info/WHEEL
odoo8_addon_sale_order_project-8.0.1.0.0.99.dev21.dist-info/namespace_packages.txt
odoo8_addon_sale_order_project-8.0.1.0.0.99.dev21.dist-info/top_level.txt
odoo8_addon_sale_order_project-8.0.1.0.0.99.dev21.dist-info/RECORD
